<!DOCTYPE suite SYSTEM "http://testng.org/testng-1.0.dtd" >

<suite name="TheSuite" verbose="0">
    <test name="Testing" parallel="classes" thread-count="5">
        <groups>
            <!-- All the tests -->
            <define name="all">
                <include name="postgresql-siard1"/>
                <include name="mysql-siard1"/>
                <include name="siard-roundtrip"/>
                <include name="cli"/>
            </define>

            <!-- Tests ran by Travis CI -->
            <define name="travis-ci">
                <include name="postgresql-siard1"/>
                <include name="mysql-siard1"/>
                <include name="siard-roundtrip"/>
                <include name="cli"/>
            </define>

            <!-- Tests that don't have external dependencies -->
            <define name="no-dependencies">
                <include name="siard-roundtrip"/>
                <include name="cli"/>
            </define>

            <!-- Default group of tests to run -->
            <run>
                <include name="no-dependencies"/>
            </run>
        </groups>
        <classes>
            <class name="com.databasepreservation.testing.integration.roundtrip.MySqlTest"/>
            <class name="com.databasepreservation.testing.integration.roundtrip.PostgreSqlTest"/>
            <class name="com.databasepreservation.testing.integration.siard.SiardTest"/>
            <class name="com.databasepreservation.testing.unit.cli.PostgreSQLModuleFactoryTest"/>
            <class name="com.databasepreservation.testing.unit.cli.SQLServerJDBCModuleFactoryTest"/>
        </classes>
    </test>
</suite>
